{
  "coord": {
    "lon": 120.7198,
    "lat": 15.0646
  },
  "weather": [
    {
      "id": 800,
      "main": "Clear",
      "description": "clear sky",
      "icon": "01n"
    }
  ],
  "base": "stations",
  "main": {
    "temp": 25.84,
    "feels_like": 26.65,
    "temp_min": 25.84,
    "temp_max": 25.84,
    "pressure": 1010,
    "humidity": 83,
    "sea_level": 1010,
    "grnd_level": 1005
  },
  "visibility": 10000,
  "wind": {
    "speed": 0.55,
    "deg": 56,
    "gust": 1.11
  },
  "clouds": {
    "all": 9
  },
  "dt": 1774637591,
  "sys": {
    "type": 1,
    "id": 8152,
    "country": "PH",
    "sunrise": 1774648544,
    "sunset": 1774692523
  },
  "timezone": 28800,
  "id": 1699805,
  "name": "Mexico",
  "cod": 200,
  "_last_updated_utc": "2026-03-27T18:53:11.030Z"
}