{
  "coord": {
    "lon": 120.7198,
    "lat": 15.0646
  },
  "weather": [
    {
      "id": 802,
      "main": "Clouds",
      "description": "scattered clouds",
      "icon": "03n"
    }
  ],
  "base": "stations",
  "main": {
    "temp": 25.85,
    "feels_like": 26.81,
    "temp_min": 25.85,
    "temp_max": 25.85,
    "pressure": 1010,
    "humidity": 89,
    "sea_level": 1010,
    "grnd_level": 1005
  },
  "visibility": 10000,
  "wind": {
    "speed": 0.4,
    "deg": 318,
    "gust": 0.53
  },
  "clouds": {
    "all": 37
  },
  "dt": 1781471361,
  "sys": {
    "country": "PH",
    "sunrise": 1781472430,
    "sunset": 1781519277
  },
  "timezone": 28800,
  "id": 1699805,
  "name": "Mexico",
  "cod": 200,
  "_last_updated_utc": "2026-06-14T21:09:21.156Z"
}