{
  "coord": {
    "lon": 120.7198,
    "lat": 15.0646
  },
  "weather": [
    {
      "id": 800,
      "main": "Clear",
      "description": "clear sky",
      "icon": "01n"
    }
  ],
  "base": "stations",
  "main": {
    "temp": 24.84,
    "feels_like": 25.52,
    "temp_min": 24.84,
    "temp_max": 24.84,
    "pressure": 1012,
    "humidity": 82,
    "sea_level": 1012,
    "grnd_level": 1007
  },
  "visibility": 10000,
  "wind": {
    "speed": 0.83,
    "deg": 25,
    "gust": 0.87
  },
  "clouds": {
    "all": 3
  },
  "dt": 1773952507,
  "sys": {
    "type": 1,
    "id": 8152,
    "country": "PH",
    "sunrise": 1773957699,
    "sunset": 1774001270
  },
  "timezone": 28800,
  "id": 1699805,
  "name": "Mexico",
  "cod": 200,
  "_last_updated_utc": "2026-03-19T20:35:07.437Z"
}